podcast_dl/__init__.py
podcast_dl/application.py
podcast_dl/cli.py
podcast_dl/config.py
podcast_dl/logger.py
podcast_dl/models.py
podcast_dl/parser.py
podcast_dl-0.0.4.dist-info/DESCRIPTION.rst
podcast_dl-0.0.4.dist-info/METADATA
podcast_dl-0.0.4.dist-info/RECORD
podcast_dl-0.0.4.dist-info/WHEEL
podcast_dl-0.0.4.dist-info/entry_points.txt
podcast_dl-0.0.4.dist-info/metadata.json
podcast_dl-0.0.4.dist-info/top_level.txt
