Metadata-Version: 2.0
Name: podcast-dl
Version: 0.0.4
Summary: Command-line program for downloading podcasts
Home-page: https://github.com/podcast-dl/podcast-dl
Author: Jorrin Pollard
Author-email: me@jorrinpollard.com
License: MIT
Keywords: podcast,podcasts,podcasting,download,downloads,downloading,scrape,scraper,scrapers,scraping,tag,tags,tagger,taggers,tagging,audio,mp3
Platform: UNKNOWN
Classifier: Development Status :: 3 - Alpha
Classifier: Environment :: Console
Classifier: Intended Audience :: End Users/Desktop
Classifier: License :: OSI Approved :: MIT License
Classifier: Natural Language :: English
Classifier: Operating System :: OS Independent
Classifier: Programming Language :: Python :: 3.6
Classifier: Topic :: Multimedia :: Sound/Audio
Requires-Dist: appdirs
Requires-Dist: bs4
Requires-Dist: click
Requires-Dist: clint
Requires-Dist: colorama
Requires-Dist: feedparser
Requires-Dist: mutagen
Requires-Dist: peewee
Requires-Dist: Pillow
Requires-Dist: python-dateutil
Requires-Dist: requests
Requires-Dist: unicode-slugify
Requires-Dist: pprint
